callgraph/__init__.py
callgraph/decorator.py
callgraph/extension.py
callgraph/instrumentor.py
callgraph/recorder.py
callgraph-1.0.0.dist-info/LICENSE
callgraph-1.0.0.dist-info/WHEEL
callgraph-1.0.0.dist-info/METADATA
callgraph-1.0.0.dist-info/RECORD
